[
  {
    "id": "5dfe6281487944ee870edb668c24c1f4",
    "group-id": null,
    "source-model": "ConstantAlphaModel(Price,Up,00:20:00,0.025)",
    "generated-time": 1381152660.0,
    "created-time": 1381152660.0,
    "close-time": 1381153860.0,
    "symbol": "SPY R735QTJ8XC9X",
    "ticker": "SPY",
    "type": "price",
    "reference": 153.01779001600,
    "reference-final": 153.38333657600,
    "direction": "up",
    "period": 1200.0,
    "magnitude": 0.025,
    "confidence": null,
    "weight": null,
    "score-final": true,
    "score-magnitude": 1.0,
    "score-direction": 1.0,
    "estimated-value": 3855.4890
  },
  {
    "id": "c6b78677b0d74b779fbf40c5d76d94d7",
    "group-id": null,
    "source-model": "ConstantAlphaModel(Price,Up,00:20:00,0.025)",
    "generated-time": 1381153860.0,
    "created-time": 1381153860.0,
    "close-time": 1381155060.0,
    "symbol": "SPY R735QTJ8XC9X",
    "ticker": "SPY",
    "type": "price",
    "reference": 153.38333657600,
    "reference-final": 153.59352584800,
    "direction": "up",
    "period": 1200.0,
    "magnitude": 0.025,
    "confidence": null,
    "weight": null,
    "score-final": true,
    "score-magnitude": 1.0,
    "score-direction": 1.0,
    "estimated-value": 840.4880
  },
  {
    "id": "83f7bd157a1c4855817a2543124911dc",
    "group-id": null,
    "source-model": "ConstantAlphaModel(Price,Up,00:20:00,0.025)",
    "generated-time": 1381155060.0,
    "created-time": 1381155060.0,
    "close-time": 1381156260.0,
    "symbol": "SPY R735QTJ8XC9X",
    "ticker": "SPY",
    "type": "price",
    "reference": 153.59352584800,
    "reference-final": 153.82199244800,
    "direction": "up",
    "period": 1200.0,
    "magnitude": 0.025,
    "confidence": null,
    "weight": null,
    "score-final": true,
    "score-magnitude": 1.0,
    "score-direction": 1.0,
    "estimated-value": 878.3992
  },
  {
    "id": "c0c8b1f0c4cb48389234ed929366dce7",
    "group-id": null,
    "source-model": "ConstantAlphaModel(Price,Up,00:20:00,0.025)",
    "generated-time": 1381156260.0,
    "created-time": 1381156260.0,
    "close-time": 1381157460.0,
    "symbol": "SPY R735QTJ8XC9X",
    "ticker": "SPY",
    "type": "price",
    "reference": 153.82199244800,
    "reference-final": 153.68491248800,
    "direction": "up",
    "period": 1200.0,
    "magnitude": 0.025,
    "confidence": null,
    "weight": null,
    "score-final": true,
    "score-magnitude": 0.0,
    "score-direction": 0.0,
    "estimated-value": -270.4341
  },
  {
    "id": "9279c7016e9849ac9439ea7b91bb4615",
    "group-id": null,
    "source-model": "ConstantAlphaModel(Price,Up,00:20:00,0.025)",
    "generated-time": 1381157460.0,
    "created-time": 1381157460.0,
    "close-time": 1381158660.0,
    "symbol": "SPY R735QTJ8XC9X",
    "ticker": "SPY",
    "type": "price",
    "reference": 153.68491248800,
    "reference-final": 153.63921916800,
    "direction": "up",
    "period": 1200.0,
    "magnitude": 0.025,
    "confidence": null,
    "weight": null,
    "score-final": true,
    "score-magnitude": 0.0,
    "score-direction": 0.0,
    "estimated-value": -24.6689
  },
  {
    "id": "fd7f2c80aacd405ba07d08714f7606d0",
    "group-id": null,
    "source-model": "ConstantAlphaModel(Price,Up,00:20:00,0.025)",
    "generated-time": 1381158660.0,
    "created-time": 1381158660.0,
    "close-time": 1381159860.0,
    "symbol": "SPY R735QTJ8XC9X",
    "ticker": "SPY",
    "type": "price",
    "reference": 153.63921916800,
    "reference-final": 153.56610985600,
    "direction": "up",
    "period": 1200.0,
    "magnitude": 0.025,
    "confidence": null,
    "weight": null,
    "score-final": true,
    "score-magnitude": 0.0,
    "score-direction": 0.0,
    "estimated-value": -130.6339
  },
  {
    "id": "ea48e0ad04d84d9a8bf2c19698db79db",
    "group-id": null,
    "source-model": "ConstantAlphaModel(Price,Up,00:20:00,0.025)",
    "generated-time": 1381159860.0,
    "created-time": 1381159860.0,
    "close-time": 1381161060.0,
    "symbol": "SPY R735QTJ8XC9X",
    "ticker": "SPY",
    "type": "price",
    "reference": 153.56610985600,
    "reference-final": 153.85854710400,
    "direction": "up",
    "period": 1200.0,
    "magnitude": 0.025,
    "confidence": null,
    "weight": null,
    "score-final": true,
    "score-magnitude": 1.0,
    "score-direction": 1.0,
    "estimated-value": 835.3412
  },
  {
    "id": "703c6bed21ba49fea5f85daaad0bba5d",
    "group-id": null,
    "source-model": "ConstantAlphaModel(Price,Up,00:20:00,0.025)",
    "generated-time": 1381161060.0,
    "created-time": 1381161060.0,
    "close-time": 1381162260.0,
    "symbol": "SPY R735QTJ8XC9X",
    "ticker": "SPY",
    "type": "price",
    "reference": 153.85854710400,
    "reference-final": 153.70318981600,
    "direction": "up",
    "period": 1200.0,
    "magnitude": 0.025,
    "confidence": null,
    "weight": null,
    "score-final": true,
    "score-magnitude": 0.0,
    "score-direction": 0.0,
    "estimated-value": -242.1135
  },
  {
    "id": "fdd49f6cbfb34c1bab32d86fb054a96a",
    "group-id": null,
    "source-model": "ConstantAlphaModel(Price,Up,00:20:00,0.025)",
    "generated-time": 1381162260.0,
    "created-time": 1381162260.0,
    "close-time": 1381163460.0,
    "symbol": "SPY R735QTJ8XC9X",
    "ticker": "SPY",
    "type": "price",
    "reference": 153.70318981600,
    "reference-final": 153.38333657600,
    "direction": "up",
    "period": 1200.0,
    "magnitude": 0.025,
    "confidence": null,
    "weight": null,
    "score-final": true,
    "score-magnitude": 0.0,
    "score-direction": 0.0,
    "estimated-value": -312.1480
  },
  {
    "id": "c202cfe4f7f34989a0f1e14965c7370e",
    "group-id": null,
    "source-model": "ConstantAlphaModel(Price,Up,00:20:00,0.025)",
    "generated-time": 1381163460.0,
    "created-time": 1381163460.0,
    "close-time": 1381164660.0,
    "symbol": "SPY R735QTJ8XC9X",
    "ticker": "SPY",
    "type": "price",
    "reference": 153.38333657600,
    "reference-final": 153.52955520000,
    "direction": "up",
    "period": 1200.0,
    "magnitude": 0.025,
    "confidence": null,
    "weight": null,
    "score-final": true,
    "score-magnitude": 1.0,
    "score-direction": 1.0,
    "estimated-value": 627.2355
  },
  {
    "id": "27ddc00e982347f4a77847ea853b2473",
    "group-id": null,
    "source-model": "ConstantAlphaModel(Price,Up,00:20:00,0.025)",
    "generated-time": 1381164660.0,
    "created-time": 1381164660.0,
    "close-time": 1381165860.0,
    "symbol": "SPY R735QTJ8XC9X",
    "ticker": "SPY",
    "type": "price",
    "reference": 153.52955520000,
    "reference-final": 153.49300054400,
    "direction": "up",
    "period": 1200.0,
    "magnitude": 0.025,
    "confidence": null,
    "weight": null,
    "score-final": true,
    "score-magnitude": 0.0,
    "score-direction": 0.0,
    "estimated-value": -18.0361
  },
  {
    "id": "770ce84688ca4f56a4cccb617a1e1794",
    "group-id": null,
    "source-model": "ConstantAlphaModel(Price,Up,00:20:00,0.025)",
    "generated-time": 1381165860.0,
    "created-time": 1381165860.0,
    "close-time": 1381167060.0,
    "symbol": "SPY R735QTJ8XC9X",
    "ticker": "SPY",
    "type": "price",
    "reference": 153.49300054400,
    "reference-final": 153.65749649600,
    "direction": "up",
    "period": 1200.0,
    "magnitude": 0.025,
    "confidence": null,
    "weight": null,
    "score-final": true,
    "score-magnitude": 1.0,
    "score-direction": 1.0,
    "estimated-value": 366.5694
  },
  {
    "id": "70b30d237910484884cbb159b27433e8",
    "group-id": null,
    "source-model": "ConstantAlphaModel(Price,Up,00:20:00,0.025)",
    "generated-time": 1381167060.0,
    "created-time": 1381167060.0,
    "close-time": 1381168260.0,
    "symbol": "SPY R735QTJ8XC9X",
    "ticker": "SPY",
    "type": "price",
    "reference": 153.65749649600,
    "reference-final": 153.53869386400,
    "direction": "up",
    "period": 1200.0,
    "magnitude": 0.025,
    "confidence": null,
    "weight": null,
    "score-final": true,
    "score-magnitude": 0.0,
    "score-direction": 0.0,
    "estimated-value": -207.8238
  },
  {
    "id": "750556da03d344e7ad701807650f54a1",
    "group-id": null,
    "source-model": "ConstantAlphaModel(Price,Up,00:20:00,0.025)",
    "generated-time": 1381168260.0,
    "created-time": 1381168260.0,
    "close-time": 1381169460.0,
    "symbol": "SPY R735QTJ8XC9X",
    "ticker": "SPY",
    "type": "price",
    "reference": 153.53869386400,
    "reference-final": 153.68491248800,
    "direction": "up",
    "period": 1200.0,
    "magnitude": 0.025,
    "confidence": null,
    "weight": null,
    "score-final": true,
    "score-magnitude": 1.0,
    "score-direction": 1.0,
    "estimated-value": 296.5577
  },
  {
    "id": "4e3db0cdcbd64e70ac0ec4e60f22513d",
    "group-id": null,
    "source-model": "ConstantAlphaModel(Price,Up,00:20:00,0.025)",
    "generated-time": 1381169460.0,
    "created-time": 1381169460.0,
    "close-time": 1381170660.0,
    "symbol": "SPY R735QTJ8XC9X",
    "ticker": "SPY",
    "type": "price",
    "reference": 153.68491248800,
    "reference-final": 153.70318981600,
    "direction": "up",
    "period": 1200.0,
    "magnitude": 0.025,
    "confidence": null,
    "weight": null,
    "score-final": true,
    "score-magnitude": 1.0,
    "score-direction": 1.0,
    "estimated-value": 42.1084
  },
  {
    "id": "09af9d7e04424c0fb3102497cf9530ef",
    "group-id": null,
    "source-model": "ConstantAlphaModel(Price,Up,00:20:00,0.025)",
    "generated-time": 1381170660.0,
    "created-time": 1381170660.0,
    "close-time": 1381171860.0,
    "symbol": "SPY R735QTJ8XC9X",
    "ticker": "SPY",
    "type": "price",
    "reference": 153.70318981600,
    "reference-final": 153.71232848000,
    "direction": "up",
    "period": 1200.0,
    "magnitude": 0.025,
    "confidence": null,
    "weight": null,
    "score-final": true,
    "score-magnitude": 1.0,
    "score-direction": 1.0,
    "estimated-value": 8.3634
  },
  {
    "id": "535d449dd14d4b29b723c0090b8ee3ff",
    "group-id": null,
    "source-model": "ConstantAlphaModel(Price,Up,00:20:00,0.025)",
    "generated-time": 1381171860.0,
    "created-time": 1381171860.0,
    "close-time": 1381173060.0,
    "symbol": "SPY R735QTJ8XC9X",
    "ticker": "SPY",
    "type": "price",
    "reference": 153.71232848000,
    "reference-final": 153.73060580800,
    "direction": "up",
    "period": 1200.0,
    "magnitude": 0.025,
    "confidence": null,
    "weight": null,
    "score-final": true,
    "score-magnitude": 1.0,
    "score-direction": 1.0,
    "estimated-value": 13.2114
  },
  {
    "id": "96583f2c95fe4f9ab9fb4b274c90b780",
    "group-id": null,
    "source-model": "ConstantAlphaModel(Price,Up,00:20:00,0.025)",
    "generated-time": 1381173060.0,
    "created-time": 1381173060.0,
    "close-time": 1381174260.0,
    "symbol": "SPY R735QTJ8XC9X",
    "ticker": "SPY",
    "type": "price",
    "reference": 153.73060580800,
    "reference-final": 153.48386188000,
    "direction": "up",
    "period": 1200.0,
    "magnitude": 0.025,
    "confidence": null,
    "weight": null,
    "score-final": true,
    "score-magnitude": 0.0,
    "score-direction": 0.0,
    "estimated-value": -316.6884
  },
  {
    "id": "fb36e9fb1ad547968c2ebce91862873d",
    "group-id": null,
    "source-model": "ConstantAlphaModel(Price,Up,00:20:00,0.025)",
    "generated-time": 1381174260.0,
    "created-time": 1381174260.0,
    "close-time": 1381175460.0,
    "symbol": "SPY R735QTJ8XC9X",
    "ticker": "SPY",
    "type": "price",
    "reference": 153.48386188000,
    "reference-final": 153.24625661600,
    "direction": "up",
    "period": 1200.0,
    "magnitude": 0.025,
    "confidence": null,
    "weight": null,
    "score-final": true,
    "score-magnitude": 0.0,
    "score-direction": 0.0,
    "estimated-value": -586.6308
  },
  {
    "id": "68ce68cfea594056ac15ca8452abee54",
    "group-id": null,
    "source-model": "ConstantAlphaModel(Price,Up,00:20:00,0.025)",
    "generated-time": 1381175460.0,
    "created-time": 1381175460.0,
    "close-time": 1381239660.0,
    "symbol": "SPY R735QTJ8XC9X",
    "ticker": "SPY",
    "type": "price",
    "reference": 153.24625661600,
    "reference-final": 152.68879811200,
    "direction": "up",
    "period": 1200.0,
    "magnitude": 0.025,
    "confidence": null,
    "weight": null,
    "score-final": true,
    "score-magnitude": 0.0,
    "score-direction": 0.0,
    "estimated-value": -3184.2085
  },
  {
    "id": "232c18ad297d4b769bca46f702e8c13a",
    "group-id": null,
    "source-model": "ConstantAlphaModel(Price,Up,00:20:00,0.025)",
    "generated-time": 1381239060.0,
    "created-time": 1381239060.0,
    "close-time": 1381240260.0,
    "symbol": "SPY R735QTJ8XC9X",
    "ticker": "SPY",
    "type": "price",
    "reference": 153.07262200000,
    "reference-final": 152.87157139200,
    "direction": "up",
    "period": 1200.0,
    "magnitude": 0.025,
    "confidence": null,
    "weight": null,
    "score-final": true,
    "score-magnitude": 0.0,
    "score-direction": 0.0,
    "estimated-value": -1602.0275
  },
  {
    "id": "184e21571dc24568b5421dc20a3c6293",
    "group-id": null,
    "source-model": "ConstantAlphaModel(Price,Up,00:20:00,0.025)",
    "generated-time": 1381240260.0,
    "created-time": 1381240260.0,
    "close-time": 1381241460.0,
    "symbol": "SPY R735QTJ8XC9X",
    "ticker": "SPY",
    "type": "price",
    "reference": 152.87157139200,
    "reference-final": 152.77104608800,
    "direction": "up",
    "period": 1200.0,
    "magnitude": 0.025,
    "confidence": null,
    "weight": null,
    "score-final": true,
    "score-magnitude": 0.0,
    "score-direction": 0.0,
    "estimated-value": -392.2316
  },
  {
    "id": "98dbd0f548674782b912250d57ce28a7",
    "group-id": null,
    "source-model": "ConstantAlphaModel(Price,Up,00:20:00,0.025)",
    "generated-time": 1381241460.0,
    "created-time": 1381241460.0,
    "close-time": 1381242660.0,
    "symbol": "SPY R735QTJ8XC9X",
    "ticker": "SPY",
    "type": "price",
    "reference": 152.77104608800,
    "reference-final": 152.97209669600,
    "direction": "up",
    "period": 1200.0,
    "magnitude": 0.025,
    "confidence": null,
    "weight": null,
    "score-final": true,
    "score-magnitude": 1.0,
    "score-direction": 1.0,
    "estimated-value": 676.0065
  },
  {
    "id": "bb1b3573ab5d470b9be69c4331880795",
    "group-id": null,
    "source-model": "ConstantAlphaModel(Price,Up,00:20:00,0.025)",
    "generated-time": 1381242660.0,
    "created-time": 1381242660.0,
    "close-time": 1381243860.0,
    "symbol": "SPY R735QTJ8XC9X",
    "ticker": "SPY",
    "type": "price",
    "reference": 152.97209669600,
    "reference-final": 152.38722220000,
    "direction": "up",
    "period": 1200.0,
    "magnitude": 0.025,
    "confidence": null,
    "weight": null,
    "score-final": true,
    "score-magnitude": 0.0,
    "score-direction": 0.0,
    "estimated-value": -978.8869
  },
  {
    "id": "3e9d8128627544aaa5df5cdf0e52e4a5",
    "group-id": null,
    "source-model": "ConstantAlphaModel(Price,Up,00:20:00,0.025)",
    "generated-time": 1381243860.0,
    "created-time": 1381243860.0,
    "close-time": 1381245060.0,
    "symbol": "SPY R735QTJ8XC9X",
    "ticker": "SPY",
    "type": "price",
    "reference": 152.38722220000,
    "reference-final": 152.43291552000,
    "direction": "up",
    "period": 1200.0,
    "magnitude": 0.025,
    "confidence": null,
    "weight": null,
    "score-final": true,
    "score-magnitude": 1.0,
    "score-direction": 1.0,
    "estimated-value": 473.7369
  },
  {
    "id": "2e3699c4ee2f4c07b8c358b6cc648dff",
    "group-id": null,
    "source-model": "ConstantAlphaModel(Price,Up,00:20:00,0.025)",
    "generated-time": 1381245060.0,
    "created-time": 1381245060.0,
    "close-time": 1381246260.0,
    "symbol": "SPY R735QTJ8XC9X",
    "ticker": "SPY",
    "type": "price",
    "reference": 152.43291552000,
    "reference-final": 152.25014224000,
    "direction": "up",
    "period": 1200.0,
    "magnitude": 0.025,
    "confidence": null,
    "weight": null,
    "score-final": true,
    "score-magnitude": 0.0,
    "score-direction": 0.0,
    "estimated-value": -744.2382
  },
  {
    "id": "9506d896695044688a387a2ed4fc6d41",
    "group-id": null,
    "source-model": "ConstantAlphaModel(Price,Up,00:20:00,0.025)",
    "generated-time": 1381246260.0,
    "created-time": 1381246260.0,
    "close-time": 1381247460.0,
    "symbol": "SPY R735QTJ8XC9X",
    "ticker": "SPY",
    "type": "price",
    "reference": 152.25014224000,
    "reference-final": 151.89373434400,
    "direction": "up",
    "period": 1200.0,
    "magnitude": 0.025,
    "confidence": null,
    "weight": null,
    "score-final": true,
    "score-magnitude": 0.0,
    "score-direction": 0.0,
    "estimated-value": -1603.3330
  },
  {
    "id": "0511c378d68740f6986f61b29cd1b937",
    "group-id": null,
    "source-model": "ConstantAlphaModel(Price,Up,00:20:00,0.025)",
    "generated-time": 1381247460.0,
    "created-time": 1381247460.0,
    "close-time": 1381248660.0,
    "symbol": "SPY R735QTJ8XC9X",
    "ticker": "SPY",
    "type": "price",
    "reference": 151.89373434400,
    "reference-final": 151.91201167200,
    "direction": "up",
    "period": 1200.0,
    "magnitude": 0.025,
    "confidence": null,
    "weight": null,
    "score-final": true,
    "score-magnitude": 1.0,
    "score-direction": 1.0,
    "estimated-value": 62.2325
  },
  {
    "id": "b855e9362b0846049b00fbfa443f205f",
    "group-id": null,
    "source-model": "ConstantAlphaModel(Price,Up,00:20:00,0.025)",
    "generated-time": 1381248660.0,
    "created-time": 1381248660.0,
    "close-time": 1381249860.0,
    "symbol": "SPY R735QTJ8XC9X",
    "ticker": "SPY",
    "type": "price",
    "reference": 151.91201167200,
    "reference-final": 151.69268373600,
    "direction": "up",
    "period": 1200.0,
    "magnitude": 0.025,
    "confidence": null,
    "weight": null,
    "score-final": true,
    "score-magnitude": 0.0,
    "score-direction": 0.0,
    "estimated-value": -450.2978
  },
  {
    "id": "74a8b430deed443e84f15248d114e6ad",
    "group-id": null,
    "source-model": "ConstantAlphaModel(Price,Up,00:20:00,0.025)",
    "generated-time": 1381249860.0,
    "created-time": 1381249860.0,
    "close-time": 1381251060.0,
    "symbol": "SPY R735QTJ8XC9X",
    "ticker": "SPY",
    "type": "price",
    "reference": 151.69268373600,
    "reference-final": 151.93942766400,
    "direction": "up",
    "period": 1200.0,
    "magnitude": 0.025,
    "confidence": null,
    "weight": null,
    "score-final": true,
    "score-magnitude": 1.0,
    "score-direction": 1.0,
    "estimated-value": 548.1219
  },
  {
    "id": "f0b3007cee5b474aa0688001b9828d80",
    "group-id": null,
    "source-model": "ConstantAlphaModel(Price,Up,00:20:00,0.025)",
    "generated-time": 1381251060.0,
    "created-time": 1381251060.0,
    "close-time": 1381252260.0,
    "symbol": "SPY R735QTJ8XC9X",
    "ticker": "SPY",
    "type": "price",
    "reference": 151.93942766400,
    "reference-final": 151.82062503200,
    "direction": "up",
    "period": 1200.0,
    "magnitude": 0.025,
    "confidence": null,
    "weight": null,
    "score-final": true,
    "score-magnitude": 0.0,
    "score-direction": 0.0,
    "estimated-value": -200.5080
  },
  {
    "id": "ca2698d440a846f081ec9c8038446134",
    "group-id": null,
    "source-model": "ConstantAlphaModel(Price,Up,00:20:00,0.025)",
    "generated-time": 1381252260.0,
    "created-time": 1381252260.0,
    "close-time": 1381253460.0,
    "symbol": "SPY R735QTJ8XC9X",
    "ticker": "SPY",
    "type": "price",
    "reference": 151.82062503200,
    "reference-final": 151.93942766400,
    "direction": "up",
    "period": 1200.0,
    "magnitude": 0.025,
    "confidence": null,
    "weight": null,
    "score-final": true,
    "score-magnitude": 1.0,
    "score-direction": 1.0,
    "estimated-value": 275.7112
  },
  {
    "id": "a100dcc440314098980e12b88cbe5d62",
    "group-id": null,
    "source-model": "ConstantAlphaModel(Price,Up,00:20:00,0.025)",
    "generated-time": 1381253460.0,
    "created-time": 1381253460.0,
    "close-time": 1381254660.0,
    "symbol": "SPY R735QTJ8XC9X",
    "ticker": "SPY",
    "type": "price",
    "reference": 151.93942766400,
    "reference-final": 151.69268373600,
    "direction": "up",
    "period": 1200.0,
    "magnitude": 0.025,
    "confidence": null,
    "weight": null,
    "score-final": true,
    "score-magnitude": 0.0,
    "score-direction": 0.0,
    "estimated-value": -881.9640
  },
  {
    "id": "463b6e8a85c24c04bc00faa6fb044cda",
    "group-id": null,
    "source-model": "ConstantAlphaModel(Price,Up,00:20:00,0.025)",
    "generated-time": 1381254660.0,
    "created-time": 1381254660.0,
    "close-time": 1381255860.0,
    "symbol": "SPY R735QTJ8XC9X",
    "ticker": "SPY",
    "type": "price",
    "reference": 151.69268373600,
    "reference-final": 151.53732644800,
    "direction": "up",
    "period": 1200.0,
    "magnitude": 0.025,
    "confidence": null,
    "weight": null,
    "score-final": true,
    "score-magnitude": 0.0,
    "score-direction": 0.0,
    "estimated-value": -229.7672
  },
  {
    "id": "7d7606554d434558bdd42cf863e08802",
    "group-id": null,
    "source-model": "ConstantAlphaModel(Price,Up,00:20:00,0.025)",
    "generated-time": 1381255860.0,
    "created-time": 1381255860.0,
    "close-time": 1381257060.0,
    "symbol": "SPY R735QTJ8XC9X",
    "ticker": "SPY",
    "type": "price",
    "reference": 151.53732644800,
    "reference-final": 151.75665438400,
    "direction": "up",
    "period": 1200.0,
    "magnitude": 0.025,
    "confidence": null,
    "weight": null,
    "score-final": true,
    "score-magnitude": 1.0,
    "score-direction": 1.0,
    "estimated-value": 366.6001
  },
  {
    "id": "974238da8f9c47bca95a9db72a5b3b30",
    "group-id": null,
    "source-model": "ConstantAlphaModel(Price,Up,00:20:00,0.025)",
    "generated-time": 1381257060.0,
    "created-time": 1381257060.0,
    "close-time": 1381258260.0,
    "symbol": "SPY R735QTJ8XC9X",
    "ticker": "SPY",
    "type": "price",
    "reference": 151.75665438400,
    "reference-final": 151.44593980800,
    "direction": "up",
    "period": 1200.0,
    "magnitude": 0.025,
    "confidence": null,
    "weight": null,
    "score-final": true,
    "score-magnitude": 0.0,
    "score-direction": 0.0,
    "estimated-value": -1150.1100
  },
  {
    "id": "1fe047eb1bf74655918166aa758334cc",
    "group-id": null,
    "source-model": "ConstantAlphaModel(Price,Up,00:20:00,0.025)",
    "generated-time": 1381258260.0,
    "created-time": 1381258260.0,
    "close-time": 1381259460.0,
    "symbol": "SPY R735QTJ8XC9X",
    "ticker": "SPY",
    "type": "price",
    "reference": 151.44593980800,
    "reference-final": 151.52818778400,
    "direction": "up",
    "period": 1200.0,
    "magnitude": 0.025,
    "confidence": null,
    "weight": null,
    "score-final": true,
    "score-magnitude": 1.0,
    "score-direction": 1.0,
    "estimated-value": 134.3323
  },
  {
    "id": "0855f250d3074e34bec31cbee2b8424e",
    "group-id": null,
    "source-model": "ConstantAlphaModel(Price,Up,00:20:00,0.025)",
    "generated-time": 1381259460.0,
    "created-time": 1381259460.0,
    "close-time": 1381260660.0,
    "symbol": "SPY R735QTJ8XC9X",
    "ticker": "SPY",
    "type": "price",
    "reference": 151.52818778400,
    "reference-final": 151.89373434400,
    "direction": "up",
    "period": 1200.0,
    "magnitude": 0.025,
    "confidence": null,
    "weight": null,
    "score-final": true,
    "score-magnitude": 1.0,
    "score-direction": 1.0,
    "estimated-value": 1066.9500
  },
  {
    "id": "f574db1b25744f8b943561f8e7fc4d5c",
    "group-id": null,
    "source-model": "ConstantAlphaModel(Price,Up,00:20:00,0.025)",
    "generated-time": 1381260660.0,
    "created-time": 1381260660.0,
    "close-time": 1381261860.0,
    "symbol": "SPY R735QTJ8XC9X",
    "ticker": "SPY",
    "type": "price",
    "reference": 151.89373434400,
    "reference-final": 151.57388110400,
    "direction": "up",
    "period": 1200.0,
    "magnitude": 0.025,
    "confidence": null,
    "weight": null,
    "score-final": true,
    "score-magnitude": 0.0,
    "score-direction": 0.0,
    "estimated-value": -924.2703
  },
  {
    "id": "98b1a78411054cba8479aa0014adc666",
    "group-id": null,
    "source-model": "ConstantAlphaModel(Price,Up,00:20:00,0.025)",
    "generated-time": 1381261860.0,
    "created-time": 1381261860.0,
    "close-time": 1381326060.0,
    "symbol": "SPY R735QTJ8XC9X",
    "ticker": "SPY",
    "type": "price",
    "reference": 151.57388110400,
    "reference-final": 151.35455316800,
    "direction": "up",
    "period": 1200.0,
    "magnitude": 0.025,
    "confidence": null,
    "weight": null,
    "score-final": true,
    "score-magnitude": 0.0,
    "score-direction": 0.0,
    "estimated-value": -1741.4156
  },
  {
    "id": "d6a9e8481bd64b1bb5e5b445252cce75",
    "group-id": null,
    "source-model": "ConstantAlphaModel(Price,Up,00:20:00,0.025)",
    "generated-time": 1381325460.0,
    "created-time": 1381325460.0,
    "close-time": 1381326660.0,
    "symbol": "SPY R735QTJ8XC9X",
    "ticker": "SPY",
    "type": "price",
    "reference": 151.47335580000,
    "reference-final": 150.97072928000,
    "direction": "up",
    "period": 1200.0,
    "magnitude": 0.025,
    "confidence": null,
    "weight": null,
    "score-final": true,
    "score-magnitude": 0.0,
    "score-direction": 0.0,
    "estimated-value": -5721.8601
  },
  {
    "id": "9d88f0acf9c048a688d4e966f6cc84a1",
    "group-id": null,
    "source-model": "ConstantAlphaModel(Price,Up,00:20:00,0.025)",
    "generated-time": 1381326660.0,
    "created-time": 1381326660.0,
    "close-time": 1381327860.0,
    "symbol": "SPY R735QTJ8XC9X",
    "ticker": "SPY",
    "type": "price",
    "reference": 150.97072928000,
    "reference-final": 151.16264122400,
    "direction": "up",
    "period": 1200.0,
    "magnitude": 0.025,
    "confidence": null,
    "weight": null,
    "score-final": true,
    "score-magnitude": 1.0,
    "score-direction": 1.0,
    "estimated-value": 1319.6057
  },
  {
    "id": "fc63478ba00641d9aff1af64125d1f5c",
    "group-id": null,
    "source-model": "ConstantAlphaModel(Price,Up,00:20:00,0.025)",
    "generated-time": 1381327860.0,
    "created-time": 1381327860.0,
    "close-time": 1381329060.0,
    "symbol": "SPY R735QTJ8XC9X",
    "ticker": "SPY",
    "type": "price",
    "reference": 151.16264122400,
    "reference-final": 151.37283049600,
    "direction": "up",
    "period": 1200.0,
    "magnitude": 0.025,
    "confidence": null,
    "weight": null,
    "score-final": true,
    "score-magnitude": 1.0,
    "score-direction": 1.0,
    "estimated-value": 801.1406
  },
  {
    "id": "a6c317389f80494ea70df8981cc9e0bc",
    "group-id": null,
    "source-model": "ConstantAlphaModel(Price,Up,00:20:00,0.025)",
    "generated-time": 1381329060.0,
    "created-time": 1381329060.0,
    "close-time": 1381330260.0,
    "symbol": "SPY R735QTJ8XC9X",
    "ticker": "SPY",
    "type": "price",
    "reference": 151.37283049600,
    "reference-final": 151.12608656800,
    "direction": "up",
    "period": 1200.0,
    "magnitude": 0.025,
    "confidence": null,
    "weight": null,
    "score-final": true,
    "score-magnitude": 0.0,
    "score-direction": 0.0,
    "estimated-value": -518.0833
  },
  {
    "id": "0759f627c73642efb7a9ba46f78a26dc",
    "group-id": null,
    "source-model": "ConstantAlphaModel(Price,Up,00:20:00,0.025)",
    "generated-time": 1381330260.0,
    "created-time": 1381330260.0,
    "close-time": 1381331460.0,
    "symbol": "SPY R735QTJ8XC9X",
    "ticker": "SPY",
    "type": "price",
    "reference": 151.12608656800,
    "reference-final": 150.65087604000,
    "direction": "up",
    "period": 1200.0,
    "magnitude": 0.025,
    "confidence": null,
    "weight": null,
    "score-final": true,
    "score-magnitude": 0.0,
    "score-direction": 0.0,
    "estimated-value": -1028.3318
  },
  {
    "id": "a111826432254dc7a16183f4e07a2496",
    "group-id": null,
    "source-model": "ConstantAlphaModel(Price,Up,00:20:00,0.025)",
    "generated-time": 1381331460.0,
    "created-time": 1381331460.0,
    "close-time": 1381332660.0,
    "symbol": "SPY R735QTJ8XC9X",
    "ticker": "SPY",
    "type": "price",
    "reference": 150.65087604000,
    "reference-final": 150.61432138400,
    "direction": "up",
    "period": 1200.0,
    "magnitude": 0.025,
    "confidence": null,
    "weight": null,
    "score-final": true,
    "score-magnitude": 0.0,
    "score-direction": 0.0,
    "estimated-value": -268.0425
  },
  {
    "id": "62fa975cc1a2414192ed3cb880122463",
    "group-id": null,
    "source-model": "ConstantAlphaModel(Price,Up,00:20:00,0.025)",
    "generated-time": 1381332660.0,
    "created-time": 1381332660.0,
    "close-time": 1381333860.0,
    "symbol": "SPY R735QTJ8XC9X",
    "ticker": "SPY",
    "type": "price",
    "reference": 150.61432138400,
    "reference-final": 150.98900660800,
    "direction": "up",
    "period": 1200.0,
    "magnitude": 0.025,
    "confidence": null,
    "weight": null,
    "score-final": true,
    "score-magnitude": 1.0,
    "score-direction": 1.0,
    "estimated-value": 1624.1218
  },
  {
    "id": "111046f9038649c88e05bae181c5ae0f",
    "group-id": null,
    "source-model": "ConstantAlphaModel(Price,Up,00:20:00,0.025)",
    "generated-time": 1381333860.0,
    "created-time": 1381333860.0,
    "close-time": 1381335060.0,
    "symbol": "SPY R735QTJ8XC9X",
    "ticker": "SPY",
    "type": "price",
    "reference": 150.98900660800,
    "reference-final": 150.97072928000,
    "direction": "up",
    "period": 1200.0,
    "magnitude": 0.025,
    "confidence": null,
    "weight": null,
    "score-final": true,
    "score-magnitude": 0.0,
    "score-direction": 0.0,
    "estimated-value": -54.5803
  },
  {
    "id": "a275824d9b2244059695b5c9694a5b2b",
    "group-id": null,
    "source-model": "ConstantAlphaModel(Price,Up,00:20:00,0.025)",
    "generated-time": 1381335060.0,
    "created-time": 1381335060.0,
    "close-time": 1381336260.0,
    "symbol": "SPY R735QTJ8XC9X",
    "ticker": "SPY",
    "type": "price",
    "reference": 150.97072928000,
    "reference-final": 150.97986794400,
    "direction": "up",
    "period": 1200.0,
    "magnitude": 0.025,
    "confidence": null,
    "weight": null,
    "score-final": true,
    "score-magnitude": 1.0,
    "score-direction": 1.0,
    "estimated-value": 17.5461
  },
  {
    "id": "e45380b190a44698a0c8b84548f4d161",
    "group-id": null,
    "source-model": "ConstantAlphaModel(Price,Up,00:20:00,0.025)",
    "generated-time": 1381336260.0,
    "created-time": 1381336260.0,
    "close-time": 1381337460.0,
    "symbol": "SPY R735QTJ8XC9X",
    "ticker": "SPY",
    "type": "price",
    "reference": 150.97986794400,
    "reference-final": 150.86106531200,
    "direction": "up",
    "period": 1200.0,
    "magnitude": 0.025,
    "confidence": null,
    "weight": null,
    "score-final": true,
    "score-magnitude": 0.0,
    "score-direction": 0.0,
    "estimated-value": -435.0386
  },
  {
    "id": "238f89c1ecbd48ee8d4cb929841d7fad",
    "group-id": null,
    "source-model": "ConstantAlphaModel(Price,Up,00:20:00,0.025)",
    "generated-time": 1381337460.0,
    "created-time": 1381337460.0,
    "close-time": 1381338660.0,
    "symbol": "SPY R735QTJ8XC9X",
    "ticker": "SPY",
    "type": "price",
    "reference": 150.86106531200,
    "reference-final": 151.07125458400,
    "direction": "up",
    "period": 1200.0,
    "magnitude": 0.025,
    "confidence": null,
    "weight": null,
    "score-final": true,
    "score-magnitude": 1.0,
    "score-direction": 1.0,
    "estimated-value": 536.7898
  },
  {
    "id": "92205f8c0e4e407386b6f918de9c0d80",
    "group-id": null,
    "source-model": "ConstantAlphaModel(Price,Up,00:20:00,0.025)",
    "generated-time": 1381338660.0,
    "created-time": 1381338660.0,
    "close-time": 1381339860.0,
    "symbol": "SPY R735QTJ8XC9X",
    "ticker": "SPY",
    "type": "price",
    "reference": 151.07125458400,
    "reference-final": 151.64699041600,
    "direction": "up",
    "period": 1200.0,
    "magnitude": 0.025,
    "confidence": null,
    "weight": null,
    "score-final": true,
    "score-magnitude": 1.0,
    "score-direction": 1.0,
    "estimated-value": 2118.5524
  },
  {
    "id": "5ec776a0609644b3904322280b85d914",
    "group-id": null,
    "source-model": "ConstantAlphaModel(Price,Up,00:20:00,0.025)",
    "generated-time": 1381339860.0,
    "created-time": 1381339860.0,
    "close-time": 1381341060.0,
    "symbol": "SPY R735QTJ8XC9X",
    "ticker": "SPY",
    "type": "price",
    "reference": 151.64699041600,
    "reference-final": 151.52818778400,
    "direction": "up",
    "period": 1200.0,
    "magnitude": 0.025,
    "confidence": null,
    "weight": null,
    "score-final": true,
    "score-magnitude": 0.0,
    "score-direction": 0.0,
    "estimated-value": -397.2594
  },
  {
    "id": "b21fdb8ea3a04e88a77858cb437b55a4",
    "group-id": null,
    "source-model": "ConstantAlphaModel(Price,Up,00:20:00,0.025)",
    "generated-time": 1381341060.0,
    "created-time": 1381341060.0,
    "close-time": 1381342260.0,
    "symbol": "SPY R735QTJ8XC9X",
    "ticker": "SPY",
    "type": "price",
    "reference": 151.52818778400,
    "reference-final": 151.68354507200,
    "direction": "up",
    "period": 1200.0,
    "magnitude": 0.025,
    "confidence": null,
    "weight": null,
    "score-final": true,
    "score-magnitude": 1.0,
    "score-direction": 1.0,
    "estimated-value": 153.7556
  },
  {
    "id": "e75f5538e1f24444a6850eb4f6642edc",
    "group-id": null,
    "source-model": "ConstantAlphaModel(Price,Up,00:20:00,0.025)",
    "generated-time": 1381342260.0,
    "created-time": 1381342260.0,
    "close-time": 1381343460.0,
    "symbol": "SPY R735QTJ8XC9X",
    "ticker": "SPY",
    "type": "price",
    "reference": 151.68354507200,
    "reference-final": 151.77493171200,
    "direction": "up",
    "period": 1200.0,
    "magnitude": 0.025,
    "confidence": null,
    "weight": null,
    "score-final": true,
    "score-magnitude": 1.0,
    "score-direction": 1.0,
    "estimated-value": 313.9414
  },
  {
    "id": "c32c453b21e448a58448becff67c6239",
    "group-id": null,
    "source-model": "ConstantAlphaModel(Price,Up,00:20:00,0.025)",
    "generated-time": 1381343460.0,
    "created-time": 1381343460.0,
    "close-time": 1381344660.0,
    "symbol": "SPY R735QTJ8XC9X",
    "ticker": "SPY",
    "type": "price",
    "reference": 151.77493171200,
    "reference-final": 151.67440640800,
    "direction": "up",
    "period": 1200.0,
    "magnitude": 0.025,
    "confidence": null,
    "weight": null,
    "score-final": true,
    "score-magnitude": 0.0,
    "score-direction": 0.0,
    "estimated-value": -651.9257
  },
  {
    "id": "00e9c0eb9a2246f4941dbb1ee40a2fd0",
    "group-id": null,
    "source-model": "ConstantAlphaModel(Price,Up,00:20:00,0.025)",
    "generated-time": 1381344660.0,
    "created-time": 1381344660.0,
    "close-time": 1381345860.0,
    "symbol": "SPY R735QTJ8XC9X",
    "ticker": "SPY",
    "type": "price",
    "reference": 151.67440640800,
    "reference-final": 151.78407037600,
    "direction": "up",
    "period": 1200.0,
    "magnitude": 0.025,
    "confidence": null,
    "weight": null,
    "score-final": true,
    "score-magnitude": 1.0,
    "score-direction": 1.0,
    "estimated-value": 142.8922
  },
  {
    "id": "486343ca161a4a248a0bedd9d62950ed",
    "group-id": null,
    "source-model": "ConstantAlphaModel(Price,Up,00:20:00,0.025)",
    "generated-time": 1381345860.0,
    "created-time": 1381345860.0,
    "close-time": 1381347060.0,
    "symbol": "SPY R735QTJ8XC9X",
    "ticker": "SPY",
    "type": "price",
    "reference": 151.78407037600,
    "reference-final": 151.69268373600,
    "direction": "up",
    "period": 1200.0,
    "magnitude": 0.025,
    "confidence": null,
    "weight": null,
    "score-final": true,
    "score-magnitude": 0.0,
    "score-direction": 0.0,
    "estimated-value": -66.6711
  },
  {
    "id": "a5d77294713340f0946b939197adf7d4",
    "group-id": null,
    "source-model": "ConstantAlphaModel(Price,Up,00:20:00,0.025)",
    "generated-time": 1381347060.0,
    "created-time": 1381347060.0,
    "close-time": 1381348260.0,
    "symbol": "SPY R735QTJ8XC9X",
    "ticker": "SPY",
    "type": "price",
    "reference": 151.69268373600,
    "reference-final": 151.35455316800,
    "direction": "up",
    "period": 1200.0,
    "magnitude": 0.025,
    "confidence": null,
    "weight": null,
    "score-final": true,
    "score-magnitude": 0.0,
    "score-direction": 0.0,
    "estimated-value": -1068.5602
  },
  {
    "id": "09f5fa9767834a9aa7d5a47a73f1a3eb",
    "group-id": null,
    "source-model": "ConstantAlphaModel(Price,Up,00:20:00,0.025)",
    "generated-time": 1381348260.0,
    "created-time": 1381348260.0,
    "close-time": 1381412460.0,
    "symbol": "SPY R735QTJ8XC9X",
    "ticker": "SPY",
    "type": "price",
    "reference": 151.35455316800,
    "reference-final": 153.21884062400,
    "direction": "up",
    "period": 1200.0,
    "magnitude": 0.025,
    "confidence": null,
    "weight": null,
    "score-final": true,
    "score-magnitude": 1.0,
    "score-direction": 1.0,
    "estimated-value": 18937.9540
  },
  {
    "id": "feec18fd9e2d4967be8f5d6b58aa5690",
    "group-id": null,
    "source-model": "ConstantAlphaModel(Price,Up,00:20:00,0.025)",
    "generated-time": 1381411860.0,
    "created-time": 1381411860.0,
    "close-time": 1381413060.0,
    "symbol": "SPY R735QTJ8XC9X",
    "ticker": "SPY",
    "type": "price",
    "reference": 152.88984872000,
    "reference-final": 153.14573131200,
    "direction": "up",
    "period": 1200.0,
    "magnitude": 0.025,
    "confidence": null,
    "weight": null,
    "score-final": true,
    "score-magnitude": 1.0,
    "score-direction": 1.0,
    "estimated-value": 3705.5023
  },
  {
    "id": "2b004a0f690b48ce8e28f3a3dd996a40",
    "group-id": null,
    "source-model": "ConstantAlphaModel(Price,Up,00:20:00,0.025)",
    "generated-time": 1381413060.0,
    "created-time": 1381413060.0,
    "close-time": 1381414260.0,
    "symbol": "SPY R735QTJ8XC9X",
    "ticker": "SPY",
    "type": "price",
    "reference": 153.14573131200,
    "reference-final": 153.31936592800,
    "direction": "up",
    "period": 1200.0,
    "magnitude": 0.025,
    "confidence": null,
    "weight": null,
    "score-final": true,
    "score-magnitude": 1.0,
    "score-direction": 1.0,
    "estimated-value": 837.4884
  },
  {
    "id": "80edc37a986d4b96b8e1a3e7feede331",
    "group-id": null,
    "source-model": "ConstantAlphaModel(Price,Up,00:20:00,0.025)",
    "generated-time": 1381414260.0,
    "created-time": 1381414260.0,
    "close-time": 1381415460.0,
    "symbol": "SPY R735QTJ8XC9X",
    "ticker": "SPY",
    "type": "price",
    "reference": 153.31936592800,
    "reference-final": 153.36505924800,
    "direction": "up",
    "period": 1200.0,
    "magnitude": 0.025,
    "confidence": null,
    "weight": null,
    "score-final": true,
    "score-magnitude": 1.0,
    "score-direction": 1.0,
    "estimated-value": 137.8677
  },
  {
    "id": "f6533ab732aa409692cf52f92e179447",
    "group-id": null,
    "source-model": "ConstantAlphaModel(Price,Up,00:20:00,0.025)",
    "generated-time": 1381415460.0,
    "created-time": 1381415460.0,
    "close-time": 1381416660.0,
    "symbol": "SPY R735QTJ8XC9X",
    "ticker": "SPY",
    "type": "price",
    "reference": 153.36505924800,
    "reference-final": 153.56610985600,
    "direction": "up",
    "period": 1200.0,
    "magnitude": 0.025,
    "confidence": null,
    "weight": null,
    "score-final": true,
    "score-magnitude": 1.0,
    "score-direction": 1.0,
    "estimated-value": 514.8806
  },
  {
    "id": "bcb12b087e8a48bf9eaa7e24242cb1c9",
    "group-id": null,
    "source-model": "ConstantAlphaModel(Price,Up,00:20:00,0.025)",
    "generated-time": 1381416660.0,
    "created-time": 1381416660.0,
    "close-time": 1381417860.0,
    "symbol": "SPY R735QTJ8XC9X",
    "ticker": "SPY",
    "type": "price",
    "reference": 153.56610985600,
    "reference-final": 153.24625661600,
    "direction": "up",
    "period": 1200.0,
    "magnitude": 0.025,
    "confidence": null,
    "weight": null,
    "score-final": true,
    "score-magnitude": 0.0,
    "score-direction": 0.0,
    "estimated-value": -1637.5622
  },
  {
    "id": "e7d01ef8500a45078801d8d9455ceaea",
    "group-id": null,
    "source-model": "ConstantAlphaModel(Price,Up,00:20:00,0.025)",
    "generated-time": 1381417860.0,
    "created-time": 1381417860.0,
    "close-time": 1381419060.0,
    "symbol": "SPY R735QTJ8XC9X",
    "ticker": "SPY",
    "type": "price",
    "reference": 153.24625661600,
    "reference-final": 153.46558455200,
    "direction": "up",
    "period": 1200.0,
    "magnitude": 0.025,
    "confidence": null,
    "weight": null,
    "score-final": true,
    "score-magnitude": 1.0,
    "score-direction": 1.0,
    "estimated-value": 426.6630
  },
  {
    "id": "afbe3239e72a46718564429bae1be9d2",
    "group-id": null,
    "source-model": "ConstantAlphaModel(Price,Up,00:20:00,0.025)",
    "generated-time": 1381419060.0,
    "created-time": 1381419060.0,
    "close-time": 1381420260.0,
    "symbol": "SPY R735QTJ8XC9X",
    "ticker": "SPY",
    "type": "price",
    "reference": 153.46558455200,
    "reference-final": 153.81285378400,
    "direction": "up",
    "period": 1200.0,
    "magnitude": 0.025,
    "confidence": null,
    "weight": null,
    "score-final": true,
    "score-magnitude": 1.0,
    "score-direction": 1.0,
    "estimated-value": 1949.7257
  },
  {
    "id": "6f82f98136fd476d86ad07f4c85ad679",
    "group-id": null,
    "source-model": "ConstantAlphaModel(Price,Up,00:20:00,0.025)",
    "generated-time": 1381420260.0,
    "created-time": 1381420260.0,
    "close-time": 1381421460.0,
    "symbol": "SPY R735QTJ8XC9X",
    "ticker": "SPY",
    "type": "price",
    "reference": 153.81285378400,
    "reference-final": 153.85854710400,
    "direction": "up",
    "period": 1200.0,
    "magnitude": 0.025,
    "confidence": null,
    "weight": null,
    "score-final": true,
    "score-magnitude": 1.0,
    "score-direction": 1.0,
    "estimated-value": 291.7770
  },
  {
    "id": "0dcb89d08f0743f88eed775ee3f3554a",
    "group-id": null,
    "source-model": "ConstantAlphaModel(Price,Up,00:20:00,0.025)",
    "generated-time": 1381421460.0,
    "created-time": 1381421460.0,
    "close-time": 1381422660.0,
    "symbol": "SPY R735QTJ8XC9X",
    "ticker": "SPY",
    "type": "price",
    "reference": 153.85854710400,
    "reference-final": 153.89510176000,
    "direction": "up",
    "period": 1200.0,
    "magnitude": 0.025,
    "confidence": null,
    "weight": null,
    "score-final": true,
    "score-magnitude": 1.0,
    "score-direction": 1.0,
    "estimated-value": 56.0079
  },
  {
    "id": "249c11ba8fa743db8d317f9f3b64fc0f",
    "group-id": null,
    "source-model": "ConstantAlphaModel(Price,Up,00:20:00,0.025)",
    "generated-time": 1381422660.0,
    "created-time": 1381422660.0,
    "close-time": 1381423860.0,
    "symbol": "SPY R735QTJ8XC9X",
    "ticker": "SPY",
    "type": "price",
    "reference": 153.89510176000,
    "reference-final": 153.90424042400,
    "direction": "up",
    "period": 1200.0,
    "magnitude": 0.025,
    "confidence": null,
    "weight": null,
    "score-final": true,
    "score-magnitude": 1.0,
    "score-direction": 1.0,
    "estimated-value": 8.4883
  },
  {
    "id": "6e7a624d02fb4474aa8069c0b2625579",
    "group-id": null,
    "source-model": "ConstantAlphaModel(Price,Up,00:20:00,0.025)",
    "generated-time": 1381423860.0,
    "created-time": 1381423860.0,
    "close-time": 1381425060.0,
    "symbol": "SPY R735QTJ8XC9X",
    "ticker": "SPY",
    "type": "price",
    "reference": 153.90424042400,
    "reference-final": 153.80371512000,
    "direction": "up",
    "period": 1200.0,
    "magnitude": 0.025,
    "confidence": null,
    "weight": null,
    "score-final": true,
    "score-magnitude": 0.0,
    "score-direction": 0.0,
    "estimated-value": -98.0051
  },
  {
    "id": "f75267f1e3c94014b87e777e7e213e65",
    "group-id": null,
    "source-model": "ConstantAlphaModel(Price,Up,00:20:00,0.025)",
    "generated-time": 1381425060.0,
    "created-time": 1381425060.0,
    "close-time": 1381426260.0,
    "symbol": "SPY R735QTJ8XC9X",
    "ticker": "SPY",
    "type": "price",
    "reference": 153.80371512000,
    "reference-final": 153.73974447200,
    "direction": "up",
    "period": 1200.0,
    "magnitude": 0.025,
    "confidence": null,
    "weight": null,
    "score-final": true,
    "score-magnitude": 0.0,
    "score-direction": 0.0,
    "estimated-value": -108.8019
  },
  {
    "id": "6c76193c29b3494fb2eb2bd14386ad7e",
    "group-id": null,
    "source-model": "ConstantAlphaModel(Price,Up,00:20:00,0.025)",
    "generated-time": 1381426260.0,
    "created-time": 1381426260.0,
    "close-time": 1381427460.0,
    "symbol": "SPY R735QTJ8XC9X",
    "ticker": "SPY",
    "type": "price",
    "reference": 153.73974447200,
    "reference-final": 153.79457645600,
    "direction": "up",
    "period": 1200.0,
    "magnitude": 0.025,
    "confidence": null,
    "weight": null,
    "score-final": true,
    "score-magnitude": 1.0,
    "score-direction": 1.0,
    "estimated-value": 93.6936
  },
  {
    "id": "7cee70c1b6814eca9363b84c1fb87efe",
    "group-id": null,
    "source-model": "ConstantAlphaModel(Price,Up,00:20:00,0.025)",
    "generated-time": 1381427460.0,
    "created-time": 1381427460.0,
    "close-time": 1381428660.0,
    "symbol": "SPY R735QTJ8XC9X",
    "ticker": "SPY",
    "type": "price",
    "reference": 153.79457645600,
    "reference-final": 153.70318981600,
    "direction": "up",
    "period": 1200.0,
    "magnitude": 0.025,
    "confidence": null,
    "weight": null,
    "score-final": true,
    "score-magnitude": 0.0,
    "score-direction": 0.0,
    "estimated-value": -1621.3553
  },
  {
    "id": "cdde58d42f1c44bcba4fa14bc830d63c",
    "group-id": null,
    "source-model": "ConstantAlphaModel(Price,Up,00:20:00,0.025)",
    "generated-time": 1381428660.0,
    "created-time": 1381428660.0,
    "close-time": 1381429860.0,
    "symbol": "SPY R735QTJ8XC9X",
    "ticker": "SPY",
    "type": "price",
    "reference": 153.70318981600,
    "reference-final": 153.72146714400,
    "direction": "up",
    "period": 1200.0,
    "magnitude": 0.025,
    "confidence": null,
    "weight": null,
    "score-final": true,
    "score-magnitude": 1.0,
    "score-direction": 1.0,
    "estimated-value": 48.9980
  },
  {
    "id": "6473cd7bf2d34e38a434cf6908fbc4a1",
    "group-id": null,
    "source-model": "ConstantAlphaModel(Price,Up,00:20:00,0.025)",
    "generated-time": 1381429860.0,
    "created-time": 1381429860.0,
    "close-time": 1381431060.0,
    "symbol": "SPY R735QTJ8XC9X",
    "ticker": "SPY",
    "type": "price",
    "reference": 153.72146714400,
    "reference-final": 153.77629912800,
    "direction": "up",
    "period": 1200.0,
    "magnitude": 0.025,
    "confidence": null,
    "weight": null,
    "score-final": true,
    "score-magnitude": 1.0,
    "score-direction": 1.0,
    "estimated-value": 104.5262
  },
  {
    "id": "071888c2c7864eb194bff3accb8442dd",
    "group-id": null,
    "source-model": "ConstantAlphaModel(Price,Up,00:20:00,0.025)",
    "generated-time": 1381431060.0,
    "created-time": 1381431060.0,
    "close-time": 1381432260.0,
    "symbol": "SPY R735QTJ8XC9X",
    "ticker": "SPY",
    "type": "price",
    "reference": 153.77629912800,
    "reference-final": 154.32461896800,
    "direction": "up",
    "period": 1200.0,
    "magnitude": 0.025,
    "confidence": null,
    "weight": null,
    "score-final": true,
    "score-magnitude": 1.0,
    "score-direction": 1.0,
    "estimated-value": 634.5267
  },
  {
    "id": "5c9f7d3b914c49dc967be18f14b185d3",
    "group-id": null,
    "source-model": "ConstantAlphaModel(Price,Up,00:20:00,0.025)",
    "generated-time": 1381432260.0,
    "created-time": 1381432260.0,
    "close-time": 1381433460.0,
    "symbol": "SPY R735QTJ8XC9X",
    "ticker": "SPY",
    "type": "price",
    "reference": 154.32461896800,
    "reference-final": 154.46169892800,
    "direction": "up",
    "period": 1200.0,
    "magnitude": 0.025,
    "confidence": null,
    "weight": null,
    "score-final": true,
    "score-magnitude": 1.0,
    "score-direction": 1.0,
    "estimated-value": 505.9004
  },
  {
    "id": "5611e9758edf436a82349f74ea2444e5",
    "group-id": null,
    "source-model": "ConstantAlphaModel(Price,Up,00:20:00,0.025)",
    "generated-time": 1381433460.0,
    "created-time": 1381433460.0,
    "close-time": 1381434660.0,
    "symbol": "SPY R735QTJ8XC9X",
    "ticker": "SPY",
    "type": "price",
    "reference": 154.46169892800,
    "reference-final": 154.35203496000,
    "direction": "up",
    "period": 1200.0,
    "magnitude": 0.025,
    "confidence": null,
    "weight": null,
    "score-final": true,
    "score-magnitude": 0.0,
    "score-direction": 0.0,
    "estimated-value": -1355.8074
  },
  {
    "id": "47ac4c14d9694fbabcdfe9814d2ff023",
    "group-id": null,
    "source-model": "ConstantAlphaModel(Price,Up,00:20:00,0.025)",
    "generated-time": 1381434660.0,
    "created-time": 1381434660.0,
    "close-time": 1381498860.0,
    "symbol": "SPY R735QTJ8XC9X",
    "ticker": "SPY",
    "type": "price",
    "reference": 154.35203496000,
    "reference-final": 154.49825358400,
    "direction": "up",
    "period": 1200.0,
    "magnitude": 0.025,
    "confidence": null,
    "weight": null,
    "score-final": true,
    "score-magnitude": 1.0,
    "score-direction": 1.0,
    "estimated-value": 810.3758
  },
  {
    "id": "7c6aedebcf724816bc8e2069752d75fe",
    "group-id": null,
    "source-model": "ConstantAlphaModel(Price,Up,00:20:00,0.025)",
    "generated-time": 1381498260.0,
    "created-time": 1381498260.0,
    "close-time": 1381499460.0,
    "symbol": "SPY R735QTJ8XC9X",
    "ticker": "SPY",
    "type": "price",
    "reference": 154.29720297600,
    "reference-final": 154.67188820000,
    "direction": "up",
    "period": 1200.0,
    "magnitude": 0.025,
    "confidence": null,
    "weight": null,
    "score-final": true,
    "score-magnitude": 1.0,
    "score-direction": 1.0,
    "estimated-value": 3572.9833
  },
  {
    "id": "81d0f51bec1e413192877380a74ba800",
    "group-id": null,
    "source-model": "ConstantAlphaModel(Price,Up,00:20:00,0.025)",
    "generated-time": 1381499460.0,
    "created-time": 1381499460.0,
    "close-time": 1381500660.0,
    "symbol": "SPY R735QTJ8XC9X",
    "ticker": "SPY",
    "type": "price",
    "reference": 154.67188820000,
    "reference-final": 154.93690945600,
    "direction": "up",
    "period": 1200.0,
    "magnitude": 0.025,
    "confidence": null,
    "weight": null,
    "score-final": true,
    "score-magnitude": 1.0,
    "score-direction": 1.0,
    "estimated-value": 643.9619
  },
  {
    "id": "c7023a48af9d4998972b463a4763b46b",
    "group-id": null,
    "source-model": "ConstantAlphaModel(Price,Up,00:20:00,0.025)",
    "generated-time": 1381500660.0,
    "created-time": 1381500660.0,
    "close-time": 1381501860.0,
    "symbol": "SPY R735QTJ8XC9X",
    "ticker": "SPY",
    "type": "price",
    "reference": 154.93690945600,
    "reference-final": 154.85466148000,
    "direction": "up",
    "period": 1200.0,
    "magnitude": 0.025,
    "confidence": null,
    "weight": null,
    "score-final": true,
    "score-magnitude": 0.0,
    "score-direction": 0.0,
    "estimated-value": -191.1986
  },
  {
    "id": "5049ce0c5ee24616b5c9dc65e83634a5",
    "group-id": null,
    "source-model": "ConstantAlphaModel(Price,Up,00:20:00,0.025)",
    "generated-time": 1381501860.0,
    "created-time": 1381501860.0,
    "close-time": 1381503060.0,
    "symbol": "SPY R735QTJ8XC9X",
    "ticker": "SPY",
    "type": "price",
    "reference": 154.85466148000,
    "reference-final": 154.53480824000,
    "direction": "up",
    "period": 1200.0,
    "magnitude": 0.025,
    "confidence": null,
    "weight": null,
    "score-final": true,
    "score-magnitude": 0.0,
    "score-direction": 0.0,
    "estimated-value": -466.7298
  },
  {
    "id": "b3d944569e4a414c966ed10c5b60bf62",
    "group-id": null,
    "source-model": "ConstantAlphaModel(Price,Up,00:20:00,0.025)",
    "generated-time": 1381503060.0,
    "created-time": 1381503060.0,
    "close-time": 1381504260.0,
    "symbol": "SPY R735QTJ8XC9X",
    "ticker": "SPY",
    "type": "price",
    "reference": 154.53480824000,
    "reference-final": 154.79069083200,
    "direction": "up",
    "period": 1200.0,
    "magnitude": 0.025,
    "confidence": null,
    "weight": null,
    "score-final": true,
    "score-magnitude": 1.0,
    "score-direction": 1.0,
    "estimated-value": 474.4959
  },
  {
    "id": "ccb9231f1eb04cf3b05031c824dea38a",
    "group-id": null,
    "source-model": "ConstantAlphaModel(Price,Up,00:20:00,0.025)",
    "generated-time": 1381504260.0,
    "created-time": 1381504260.0,
    "close-time": 1381505460.0,
    "symbol": "SPY R735QTJ8XC9X",
    "ticker": "SPY",
    "type": "price",
    "reference": 154.79069083200,
    "reference-final": 154.81810682400,
    "direction": "up",
    "period": 1200.0,
    "magnitude": 0.025,
    "confidence": null,
    "weight": null,
    "score-final": true,
    "score-magnitude": 1.0,
    "score-direction": 1.0,
    "estimated-value": 53.7795
  },
  {
    "id": "6879dd61324842528628dae2ce7337ca",
    "group-id": null,
    "source-model": "ConstantAlphaModel(Price,Up,00:20:00,0.025)",
    "generated-time": 1381505460.0,
    "created-time": 1381505460.0,
    "close-time": 1381506660.0,
    "symbol": "SPY R735QTJ8XC9X",
    "ticker": "SPY",
    "type": "price",
    "reference": 154.81810682400,
    "reference-final": 155.17451472000,
    "direction": "up",
    "period": 1200.0,
    "magnitude": 0.025,
    "confidence": null,
    "weight": null,
    "score-final": true,
    "score-magnitude": 1.0,
    "score-direction": 1.0,
    "estimated-value": 570.1243
  },
  {
    "id": "04ca61c4221f4e449b15adf0ca1523ac",
    "group-id": null,
    "source-model": "ConstantAlphaModel(Price,Up,00:20:00,0.025)",
    "generated-time": 1381506660.0,
    "created-time": 1381506660.0,
    "close-time": 1381507860.0,
    "symbol": "SPY R735QTJ8XC9X",
    "ticker": "SPY",
    "type": "price",
    "reference": 155.17451472000,
    "reference-final": 155.38470399200,
    "direction": "up",
    "period": 1200.0,
    "magnitude": 0.025,
    "confidence": null,
    "weight": null,
    "score-final": true,
    "score-magnitude": 1.0,
    "score-direction": 1.0,
    "estimated-value": 564.5894
  },
  {
    "id": "b93c7b5b2745408f920631e917067731",
    "group-id": null,
    "source-model": "ConstantAlphaModel(Price,Up,00:20:00,0.025)",
    "generated-time": 1381507860.0,
    "created-time": 1381507860.0,
    "close-time": 1381509060.0,
    "symbol": "SPY R735QTJ8XC9X",
    "ticker": "SPY",
    "type": "price",
    "reference": 155.38470399200,
    "reference-final": 155.46695196800,
    "direction": "up",
    "period": 1200.0,
    "magnitude": 0.025,
    "confidence": null,
    "weight": null,
    "score-final": true,
    "score-magnitude": 1.0,
    "score-direction": 1.0,
    "estimated-value": 351.1577
  },
  {
    "id": "70c3162be16f45f088020dc9e12a2876",
    "group-id": null,
    "source-model": "ConstantAlphaModel(Price,Up,00:20:00,0.025)",
    "generated-time": 1381509060.0,
    "created-time": 1381509060.0,
    "close-time": 1381510260.0,
    "symbol": "SPY R735QTJ8XC9X",
    "ticker": "SPY",
    "type": "price",
    "reference": 155.46695196800,
    "reference-final": 155.48522929600,
    "direction": "up",
    "period": 1200.0,
    "magnitude": 0.025,
    "confidence": null,
    "weight": null,
    "score-final": true,
    "score-magnitude": 1.0,
    "score-direction": 1.0,
    "estimated-value": 29.0588
  },
  {
    "id": "d77c2cd4f08446c99c438f57a027760a",
    "group-id": null,
    "source-model": "ConstantAlphaModel(Price,Up,00:20:00,0.025)",
    "generated-time": 1381510260.0,
    "created-time": 1381510260.0,
    "close-time": 1381511460.0,
    "symbol": "SPY R735QTJ8XC9X",
    "ticker": "SPY",
    "type": "price",
    "reference": 155.48522929600,
    "reference-final": 155.62230925600,
    "direction": "up",
    "period": 1200.0,
    "magnitude": 0.025,
    "confidence": null,
    "weight": null,
    "score-final": true,
    "score-magnitude": 1.0,
    "score-direction": 1.0,
    "estimated-value": 163.6639
  },
  {
    "id": "0f141401ab164fc3a44960d5bab7a6aa",
    "group-id": null,
    "source-model": "ConstantAlphaModel(Price,Up,00:20:00,0.025)",
    "generated-time": 1381511460.0,
    "created-time": 1381511460.0,
    "close-time": 1381512660.0,
    "symbol": "SPY R735QTJ8XC9X",
    "ticker": "SPY",
    "type": "price",
    "reference": 155.62230925600,
    "reference-final": 155.40298132000,
    "direction": "up",
    "period": 1200.0,
    "magnitude": 0.025,
    "confidence": null,
    "weight": null,
    "score-final": true,
    "score-magnitude": 0.0,
    "score-direction": 0.0,
    "estimated-value": -326.1845
  },
  {
    "id": "5ed52a668e2c4f4e89ad3d8a872c2bb3",
    "group-id": null,
    "source-model": "ConstantAlphaModel(Price,Up,00:20:00,0.025)",
    "generated-time": 1381512660.0,
    "created-time": 1381512660.0,
    "close-time": 1381513860.0,
    "symbol": "SPY R735QTJ8XC9X",
    "ticker": "SPY",
    "type": "price",
    "reference": 155.40298132000,
    "reference-final": 155.33901067200,
    "direction": "up",
    "period": 1200.0,
    "magnitude": 0.025,
    "confidence": null,
    "weight": null,
    "score-final": true,
    "score-magnitude": 0.0,
    "score-direction": 0.0,
    "estimated-value": -51.3179
  },
  {
    "id": "e8a7e1e3b45742dfaa300ee4c23d9b7c",
    "group-id": null,
    "source-model": "ConstantAlphaModel(Price,Up,00:20:00,0.025)",
    "generated-time": 1381513860.0,
    "created-time": 1381513860.0,
    "close-time": 1381515060.0,
    "symbol": "SPY R735QTJ8XC9X",
    "ticker": "SPY",
    "type": "price",
    "reference": 155.33901067200,
    "reference-final": 155.50350662400,
    "direction": "up",
    "period": 1200.0,
    "magnitude": 0.025,
    "confidence": null,
    "weight": null,
    "score-final": true,
    "score-magnitude": 1.0,
    "score-direction": 1.0,
    "estimated-value": 199.3921
  },
  {
    "id": "7ecaddce8446498c9c4b78014fe00c6b",
    "group-id": null,
    "source-model": "ConstantAlphaModel(Price,Up,00:20:00,0.025)",
    "generated-time": 1381515060.0,
    "created-time": 1381515060.0,
    "close-time": 1381516260.0,
    "symbol": "SPY R735QTJ8XC9X",
    "ticker": "SPY",
    "type": "price",
    "reference": 155.50350662400,
    "reference-final": 155.45781330400,
    "direction": "up",
    "period": 1200.0,
    "magnitude": 0.025,
    "confidence": null,
    "weight": null,
    "score-final": true,
    "score-magnitude": 0.0,
    "score-direction": 0.0,
    "estimated-value": -71.8409
  },
  {
    "id": "e474fb17982f450b96da7cee72b2f32c",
    "group-id": null,
    "source-model": "ConstantAlphaModel(Price,Up,00:20:00,0.025)",
    "generated-time": 1381516260.0,
    "created-time": 1381516260.0,
    "close-time": 1381517460.0,
    "symbol": "SPY R735QTJ8XC9X",
    "ticker": "SPY",
    "type": "price",
    "reference": 155.45781330400,
    "reference-final": 155.41211998400,
    "direction": "up",
    "period": 1200.0,
    "magnitude": 0.025,
    "confidence": null,
    "weight": null,
    "score-final": true,
    "score-magnitude": 0.0,
    "score-direction": 0.0,
    "estimated-value": -45.0143
  },
  {
    "id": "ca0b854b2c2f4cc7be27b5ca6e8fea77",
    "group-id": null,
    "source-model": "ConstantAlphaModel(Price,Up,00:20:00,0.025)",
    "generated-time": 1381517460.0,
    "created-time": 1381517460.0,
    "close-time": 1381518660.0,
    "symbol": "SPY R735QTJ8XC9X",
    "ticker": "SPY",
    "type": "price",
    "reference": 155.41211998400,
    "reference-final": 155.37556532800,
    "direction": "up",
    "period": 1200.0,
    "magnitude": 0.025,
    "confidence": null,
    "weight": null,
    "score-final": true,
    "score-magnitude": 0.0,
    "score-direction": 0.0,
    "estimated-value": -35.2299
  },
  {
    "id": "a2752957d8154255a61b5cbea990f0d4",
    "group-id": null,
    "source-model": "ConstantAlphaModel(Price,Up,00:20:00,0.025)",
    "generated-time": 1381518660.0,
    "created-time": 1381518660.0,
    "close-time": 1381519860.0,
    "symbol": "SPY R735QTJ8XC9X",
    "ticker": "SPY",
    "type": "price",
    "reference": 155.37556532800,
    "reference-final": 155.43039731200,
    "direction": "up",
    "period": 1200.0,
    "magnitude": 0.025,
    "confidence": null,
    "weight": null,
    "score-final": true,
    "score-magnitude": 1.0,
    "score-direction": 1.0,
    "estimated-value": 61.0439
  },
  {
    "id": "39b8679aed3e4d8a891ae028c138b2a5",
    "group-id": null,
    "source-model": "ConstantAlphaModel(Price,Up,00:20:00,0.025)",
    "generated-time": 1381519860.0,
    "created-time": 1381519860.0,
    "close-time": 1381521060.0,
    "symbol": "SPY R735QTJ8XC9X",
    "ticker": "SPY",
    "type": "price",
    "reference": 155.43039731200,
    "reference-final": 155.19279204800,
    "direction": "up",
    "period": 1200.0,
    "magnitude": 0.025,
    "confidence": null,
    "weight": null,
    "score-final": true,
    "score-magnitude": 0.0,
    "score-direction": 0.0,
    "estimated-value": -1326.6381
  },
  {
    "id": "41b82865f8ad4c6f8f7f33063fc73f7b",
    "group-id": null,
    "source-model": "ConstantAlphaModel(Price,Up,00:20:00,0.025)",
    "generated-time": 1381521060.0,
    "created-time": 1381521060.0,
    "close-time": 1381758060.0,
    "symbol": "SPY R735QTJ8XC9X",
    "ticker": "SPY",
    "type": "price",
    "reference": 155.19279204800,
    "reference-final": 0.0,
    "direction": "up",
    "period": 1200.0,
    "magnitude": 0.025,
    "confidence": null,
    "weight": null,
    "score-final": false,
    "score-magnitude": 1.0,
    "score-direction": 1.0,
    "estimated-value": 0.0
  }
]